.gitignore
LICENSE
MANIFEST.in
README.rst
requirements.txt
setup.py
test.cfg
doc/Makefile
doc/appendices.rst
doc/autocmd.py
doc/changelog.rst
doc/commands.rst
doc/conf.py
doc/fabric.rst
doc/index.rst
doc/introduction.rst
doc/manifest.rst
doc/_static/.empty
doc/_templates/.empty
examples/clojure/.gitignore
examples/clojure/.ravello.yml
examples/clojure/README.md
examples/clojure/project.clj
examples/clojure/src/hello/core.clj
examples/clojure/test/hello/core_test.clj
examples/fabric/fabfile.py
examples/fabric/hello.py
examples/fabric/scripts/schema.sql
examples/fabric/scripts/setup-db.sh
examples/fabric/scripts/setup-web.sh
examples/maven/.gitignore
examples/maven/.ravello.yml
examples/maven/pom.xml
examples/maven/src/main/java/com/ravellosystems/hello/App.java
examples/maven/src/test/java/com/ravellosystems/hello/AppTest.java
examples/multivm/.gitignore
examples/multivm/.ravello.yml
examples/multivm/development.ini
examples/multivm/production.ini
examples/multivm/requirements.txt
examples/multivm/setup.cfg
examples/multivm/setup.py
examples/multivm/blog/__init__.py
examples/multivm/blog/models.py
examples/multivm/blog/security.py
examples/multivm/blog/tests.py
examples/multivm/blog/views.py
examples/multivm/blog/scripts/__init__.py
examples/multivm/blog/scripts/initializedb.py
examples/multivm/blog/static/favicon.ico
examples/multivm/blog/static/footerbg.png
examples/multivm/blog/static/headerbg.png
examples/multivm/blog/static/ie6.css
examples/multivm/blog/static/middlebg.png
examples/multivm/blog/static/pylons.css
examples/multivm/blog/static/pyramid-small.png
examples/multivm/blog/static/pyramid.png
examples/multivm/blog/static/transparent.gif
examples/multivm/blog/templates/edit.pt
examples/multivm/blog/templates/login.pt
examples/multivm/blog/templates/view.pt
examples/multivm/deploy/setup-postgres.sh
examples/platforms/.gitignore
examples/platforms/.ravello.yml
examples/python/.gitignore
examples/python/.ravello.yml
examples/python/setup.py
lib/testmill.egg-info/PKG-INFO
lib/testmill.egg-info/SOURCES.txt
lib/testmill.egg-info/dependency_links.txt
lib/testmill.egg-info/entry_points.txt
lib/testmill.egg-info/requires.txt
lib/testmill.egg-info/top_level.txt
