Metadata-Version: 1.0
Name: testmill
Version: 0.9.11
Summary: Create multi-VM application environments for dev/test.
Home-page: https://github.com/ravello/testmill
Author: Geert Jansen
Author-email: geert.jansen@ravellosystems.com
License: Apache 2.0
Platform: UNKNOWN
Classifier: Development Status :: 4 - Beta
Classifier: License :: OSI Approved :: Apache Software License
Classifier: Operating System :: POSIX
Classifier: Operating System :: MacOS :: MacOS X
Classifier: Programming Language :: Python :: 2.6
Classifier: Programming Language :: Python :: 2.7
